spproto/__init__.py
spproto/auth.py
spproto/client.py
spproto/connection.py
spproto/key.py
spproto/server.py
spproto/protocol/__init__.py
spproto/protocol/abc.py
spproto/protocol/message.py
spproto/protocol/signed.py
spproto/transport/__init__.py
spproto/transport/abc.py
spproto/transport/stream.py
spproto-0.2.3.dist-info/METADATA
spproto-0.2.3.dist-info/WHEEL
spproto-0.2.3.dist-info/licenses/LICENSE
spproto-0.2.3.dist-info/RECORD
