Metadata-Version: 2.4
Name: spproto
Version: 0.2.3
Summary: Secure Peer Protocol
Project-URL: Homepage, https://github.com/lifr0m/spproto
Author: Lifr0m
License: MIT License
License-File: LICENSE
Keywords: chacha20,chacha20-poly1305,chat,concatkdf,cryptography,dh,ec,ecdh,ecdhe,ecdsa,ed25519,eddsa,kdf,message,peer,poly1305,protocol,secure
Classifier: License :: OSI Approved :: MIT License
Classifier: Operating System :: OS Independent
Classifier: Programming Language :: Python :: 3
Classifier: Typing :: Typed
Requires-Python: >=3.12
Requires-Dist: cryptography~=43.0.0
Provides-Extra: dev
Requires-Dist: mypy; extra == 'dev'
Requires-Dist: ruff; extra == 'dev'
